aoc_test-0.2.data/scripts/aoct
src/aoc_test/__init__.py
aoc_test-0.2.dist-info/METADATA
aoc_test-0.2.dist-info/WHEEL
aoc_test-0.2.dist-info/top_level.txt
aoc_test-0.2.dist-info/RECORD
